process_viewer/__init__.py
process_viewer/keybindings.py
process_viewer/main.py
process_viewer/process_manager.py
process_viewer/resource_graphs.py
process_viewer/ui_components.py
process_viewer/utils.py
process_viewer-0.1.6.dist-info/LICENSE
process_viewer-0.1.6.dist-info/METADATA
process_viewer-0.1.6.dist-info/WHEEL
process_viewer-0.1.6.dist-info/entry_points.txt
process_viewer-0.1.6.dist-info/top_level.txt
process_viewer-0.1.6.dist-info/RECORD
